.gitignore
LICENSE
README.md
pyproject.toml
requirements.txt
requirements_dev.txt
setup.cfg
setup.py
tox.ini
.github/ISSUE_TEMPLATE/bug_report.md
.github/ISSUE_TEMPLATE/feature_request.md
.github/workflows/coverage.yaml
.github/workflows/tests.yaml
src/mendotapy/__init__.py
src/mendotapy/mendotapy.py
src/mendotapy/py.typed
src/mendotapy.egg-info/PKG-INFO
src/mendotapy.egg-info/SOURCES.txt
src/mendotapy.egg-info/dependency_links.txt
src/mendotapy.egg-info/not-zip-safe
src/mendotapy.egg-info/requires.txt
src/mendotapy.egg-info/top_level.txt
tests/__init__.py
tests/test_mendotapy.py